{"id":160,"name":"Feraligatr","baseAttack":205,"baseDefense":188,"baseStamina":198,"types":{"primary":"water","secondary":null},"moves":{"quick":[{"id":202,"name":"Bite","type":"dark","legacy":false,"exclusive":false},{"id":327,"name":"Ice Fang","type":"ice","legacy":false,"exclusive":false},{"id":283,"name":"Waterfall","type":"water","legacy":false,"exclusive":false},{"id":230,"name":"Water Gun","type":"water","legacy":true,"exclusive":false}],"charged":[{"id":279,"name":"Crunch","type":"dark","legacy":false,"exclusive":false},{"id":299,"name":"Hydro Cannon","type":"water","legacy":true,"exclusive":false},{"id":107,"name":"Hydro Pump","type":"water","legacy":false,"exclusive":false},{"id":39,"name":"Ice Beam","type":"ice","legacy":false,"exclusive":false}]}}