{"id":79,"name":"Slowpoke","baseAttack":109,"baseDefense":98,"baseStamina":207,"types":{"primary":"water","secondary":"psychic"},"moves":{"quick":[{"id":235,"name":"Confusion","type":"psychic","legacy":false,"exclusive":false},{"id":230,"name":"Water Gun","type":"water","legacy":false,"exclusive":false}],"charged":[{"id":108,"name":"Psychic","type":"psychic","legacy":false,"exclusive":false},{"id":60,"name":"Psyshock","type":"psychic","legacy":false,"exclusive":false},{"id":105,"name":"Water Pulse","type":"water","legacy":false,"exclusive":false}]}}