{"id":809,"name":"Melmetal","baseAttack":226,"baseDefense":190,"baseStamina":264,"types":{"primary":"steel","secondary":null},"moves":{"quick":[{"id":205,"name":"Thunder Shock","type":"electric","legacy":false,"exclusive":false}],"charged":[{"id":36,"name":"Flash Cannon","type":"steel","legacy":false,"exclusive":false},{"id":14,"name":"Hyper Beam","type":"normal","legacy":false,"exclusive":false},{"id":64,"name":"Rock Slide","type":"rock","legacy":false,"exclusive":false},{"id":310,"name":"Superpower","type":"fighting","legacy":false,"exclusive":false},{"id":79,"name":"Thunderbolt","type":"electric","legacy":false,"exclusive":false}]}}